starmerx_url/__init__.py
starmerx_url/verify_url.py
starmerx_url-0.1.7.dist-info/LICENSE
starmerx_url-0.1.7.dist-info/METADATA
starmerx_url-0.1.7.dist-info/WHEEL
starmerx_url-0.1.7.dist-info/top_level.txt
starmerx_url-0.1.7.dist-info/zip-safe
starmerx_url-0.1.7.dist-info/RECORD
