Metadata-Version: 2.1
Name: starmerx-url
Version: 0.1.7
Summary: starmerx verify url
Home-page: 
Author: yang
Author-email: yangjuan@starmerx.com
License: MIT
Classifier: Environment :: Web Environment
Classifier: Intended Audience :: Developers
Classifier: Natural Language :: English
Classifier: Operating System :: Unix
Classifier: Topic :: Software Development :: Libraries :: Python Modules
Classifier: Programming Language :: Python
License-File: LICENSE
